aitronos_logger/__init__.py
aitronos_logger/logger.py
aitronos_logger-0.1.13.dist-info/METADATA
aitronos_logger-0.1.13.dist-info/WHEEL
aitronos_logger-0.1.13.dist-info/top_level.txt
aitronos_logger-0.1.13.dist-info/RECORD
