Metadata-Version: 2.1
Name: aitronos-logger
Version: 0.1.13
Summary: A Python logger for automation processes
Author-email: Demo User <demo@example.com>
Requires-Python: >=3.7
